{
  "header-a": {
    "id": 10,
    "name": "Header A",
    "class": "header-a"
  },
  "header-b": {
    "id": 11,
    "name": "Header B",
    "class": "header-b"
  },
  "section-a": {
    "id": 20,
    "name": "Section A",
    "class": "section-a"
  },
  "section-b": {
    "id": 21,
    "name": "Section B",
    "class": "section-b"
  },
  "section-c": {
    "id": 22,
    "name": "Section C",
    "class": "section-c"
  },
  "banner-a": {
    "id": 30,
    "name": "Banner A",
    "class": "banner-a"
  },
  "banner-b": {
    "id": 31,
    "name": "Banner B",
    "class": "banner-b"
  },
  "tmp": {
    "id": 9999999,
    "name": " ",
    "class": "preview--large",
    "title": true,
    "description": true,
    "event": true,
    "date": true,
    "author": true,
    "content": true,
    "link": true,
    "image": true,
    "imageFull": true,
    "contactForm": true,
    "cta": true
  }
}
